ros2dev/__init__.py
ros2dev/ros2dev.py
ros2dev/templates/Dockerfile
ros2dev/templates/docker-compose.yml
ros2dev/templates/services
ros2dev/templates/third_party.example
ros2dev/templates/workspace_copy_dir
ros2dev-0.1.6.dist-info/METADATA
ros2dev-0.1.6.dist-info/WHEEL
ros2dev-0.1.6.dist-info/entry_points.txt
ros2dev-0.1.6.dist-info/top_level.txt
ros2dev-0.1.6.dist-info/RECORD
