Metadata-Version: 2.1
Name: ros2dev
Version: 0.1.6
Summary: Setup a ROS 2.0 development environment in Docker
Home-page: https://www.kevindemarco.com
Author: Kevin DeMarco
Author-email: kevin.demarco@gmail.com
License: GPLv3
Keywords: ROS robots
Platform: UNKNOWN
Requires-Dist: argparse
Requires-Dist: jinja2
